graphrag_webui/__init__.py
graphrag_webui/main.py
graphrag_webui-1.2.0.dist-info/METADATA
graphrag_webui-1.2.0.dist-info/WHEEL
graphrag_webui-1.2.0.dist-info/entry_points.txt
graphrag_webui-1.2.0.dist-info/top_level.txt
graphrag_webui-1.2.0.dist-info/RECORD
