Metadata-Version: 2.2
Name: graphrag_webui
Version: 1.2.0
Summary: A web interface for GraphRAG.
Home-page: https://github.com/theodoreniu/graphrag_webui
Author: Theodoree
Author-email: theodore.niu@gmail.com
Classifier: Programming Language :: Python :: 3
Classifier: License :: OSI Approved :: MIT License
Classifier: Operating System :: OS Independent
Requires-Python: >=3.6
Requires-Dist: click
Dynamic: author
Dynamic: author-email
Dynamic: classifier
Dynamic: description
Dynamic: description-content-type
Dynamic: home-page
Dynamic: requires-dist
Dynamic: requires-python
Dynamic: summary
